dailydotdev_bookmark_cli/__init__.py
dailydotdev_bookmark_cli/__main__.py
dailydotdev_bookmark_cli/bookmarks.py
dailydotdev_bookmark_cli/change_dailyid.py
dailydotdev_bookmark_cli/dailydotdev_bookmark_cli.py
dailydotdev_bookmark_cli/delete_dailyid.py
dailydotdev_bookmark_cli/tui.py
dailydotdev_bookmark_cli-0.1.76.dist-info/METADATA
dailydotdev_bookmark_cli-0.1.76.dist-info/WHEEL
dailydotdev_bookmark_cli-0.1.76.dist-info/entry_points.txt
dailydotdev_bookmark_cli-0.1.76.dist-info/top_level.txt
dailydotdev_bookmark_cli-0.1.76.dist-info/RECORD
