Metadata-Version: 2.1
Name: dailydotdev-bookmark-cli
Version: 0.1.76
Summary: Get your Daily Dev bookmarks from CLI
Home-page: https://github.com/Mr-Destructive/bookmarks-cli
Author: Meet Gor
Author-email: gormeet711@gmail.com
License: UNKNOWN
Platform: UNKNOWN
Requires-Dist: feedparser
Requires-Dist: rich
Requires-Dist: textual
